ofa2/__init__.py
ofa2/model_zoo.py
ofa2/imagenet_classification/__init__.py
ofa2/imagenet_classification/data_providers/__init__.py
ofa2/imagenet_classification/data_providers/base_provider.py
ofa2/imagenet_classification/data_providers/imagenet.py
ofa2/imagenet_classification/elastic_nn/__init__.py
ofa2/imagenet_classification/elastic_nn/utils.py
ofa2/imagenet_classification/elastic_nn/modules/__init__.py
ofa2/imagenet_classification/elastic_nn/modules/dynamic_layers.py
ofa2/imagenet_classification/elastic_nn/modules/dynamic_op.py
ofa2/imagenet_classification/elastic_nn/networks/__init__.py
ofa2/imagenet_classification/elastic_nn/networks/ofa_mbv3.py
ofa2/imagenet_classification/elastic_nn/networks/ofa_proxyless.py
ofa2/imagenet_classification/elastic_nn/networks/ofa_resnets.py
ofa2/imagenet_classification/elastic_nn/training/__init__.py
ofa2/imagenet_classification/elastic_nn/training/progressive_shrinking.py
ofa2/imagenet_classification/networks/__init__.py
ofa2/imagenet_classification/networks/mobilenet_v3.py
ofa2/imagenet_classification/networks/proxyless_nets.py
ofa2/imagenet_classification/networks/resnets.py
ofa2/imagenet_classification/run_manager/__init__.py
ofa2/imagenet_classification/run_manager/distributed_run_manager.py
ofa2/imagenet_classification/run_manager/run_config.py
ofa2/imagenet_classification/run_manager/run_manager.py
ofa2/nas/__init__.py
ofa2/nas/accuracy_predictor/__init__.py
ofa2/nas/accuracy_predictor/acc_dataset.py
ofa2/nas/accuracy_predictor/acc_predictor.py
ofa2/nas/accuracy_predictor/arch_encoder.py
ofa2/nas/efficiency_predictor/__init__.py
ofa2/nas/efficiency_predictor/latency_lookup_table.py
ofa2/nas/search_algorithm/__init__.py
ofa2/nas/search_algorithm/evolution.py
ofa2/tutorial/__init__.py
ofa2/tutorial/accuracy_predictor.py
ofa2/tutorial/evolution_finder.py
ofa2/tutorial/flops_table.py
ofa2/tutorial/imagenet_eval_helper.py
ofa2/tutorial/latency_table.py
ofa2/tutorial/multi_objective_optimization.py
ofa2/utils/__init__.py
ofa2-0.1.0.post202306071524.dist-info/LICENSE
ofa2-0.1.0.post202306071524.dist-info/METADATA
ofa2-0.1.0.post202306071524.dist-info/WHEEL
ofa2-0.1.0.post202306071524.dist-info/top_level.txt
ofa2-0.1.0.post202306071524.dist-info/zip-safe
ofa2-0.1.0.post202306071524.dist-info/RECORD
