Metadata-Version: 2.1
Name: ofa2
Version: 0.1.0.post202306071524
Summary: Train one network, Search once, Deploy in many scenarios.
Home-page: https://github.com/ito-rafael/once-for-all-2
Author: Rafael Ito
Author-email: ito.rafael@gmail.com
License: MIT
Classifier: Programming Language :: Python :: 3
License-File: LICENSE
Requires-Dist: torch
